[{"element":"architecture-trois-tiers","parent":"/","isDirectory":true,"label":"architecture trois tiers","path":"architecture-trois-tiers","children":[{"element":"index.mdx","parent":"\\architecture-trois-tiers","isDirectory":false,"label":"index","path":"index"},{"element":"introduction.mdx","parent":"\\architecture-trois-tiers","isDirectory":false,"label":"introduction","path":"introduction"}]},{"element":"git","parent":"/","isDirectory":true,"label":"git","path":"git","children":[{"element":"advanced-concepts.mdx","parent":"\\git","isDirectory":false,"label":"advanced concepts","path":"advanced-concepts"},{"element":"first-steps.mdx","parent":"\\git","isDirectory":false,"label":"first steps","path":"first-steps"},{"element":"index.mdx","parent":"\\git","isDirectory":false,"label":"index","path":"index"},{"element":"intermediates-concepts.mdx","parent":"\\git","isDirectory":false,"label":"intermediates concepts","path":"intermediates-concepts"},{"element":"introduction.mdx","parent":"\\git","isDirectory":false,"label":"introduction","path":"introduction"},{"element":"project-gestion-with-git.mdx","parent":"\\git","isDirectory":false,"label":"project gestion with git","path":"project-gestion-with-git"}]}]